idpyoidc/__init__.py
idpyoidc/alg_info.py
idpyoidc/claims.py
idpyoidc/configure.py
idpyoidc/constant.py
idpyoidc/context.py
idpyoidc/converter.py
idpyoidc/defaults.py
idpyoidc/encrypter.py
idpyoidc/exception.py
idpyoidc/impexp.py
idpyoidc/item.py
idpyoidc/logging.py
idpyoidc/node.py
idpyoidc/ssl_context.py
idpyoidc/time_util.py
idpyoidc/transform.py
idpyoidc/util.py
idpyoidc/client/__init__.py
idpyoidc/client/client_auth.py
idpyoidc/client/configure.py
idpyoidc/client/cookie.py
idpyoidc/client/current.py
idpyoidc/client/defaults.py
idpyoidc/client/entity.py
idpyoidc/client/entity_metadata.py
idpyoidc/client/exception.py
idpyoidc/client/http.py
idpyoidc/client/request_object.py
idpyoidc/client/rp_handler.py
idpyoidc/client/service.py
idpyoidc/client/service_context.py
idpyoidc/client/util.py
idpyoidc/client/claims/__init__.py
idpyoidc/client/claims/oauth2.py
idpyoidc/client/claims/oauth2resource.py
idpyoidc/client/claims/oidc.py
idpyoidc/client/oauth2/__init__.py
idpyoidc/client/oauth2/access_token.py
idpyoidc/client/oauth2/authorization.py
idpyoidc/client/oauth2/client_credentials.py
idpyoidc/client/oauth2/introspection.py
idpyoidc/client/oauth2/refresh_access_token.py
idpyoidc/client/oauth2/registration.py
idpyoidc/client/oauth2/resource.py
idpyoidc/client/oauth2/resource_owner_password_credentials.py
idpyoidc/client/oauth2/server_metadata.py
idpyoidc/client/oauth2/stand_alone_client.py
idpyoidc/client/oauth2/token_exchange.py
idpyoidc/client/oauth2/token_revocation.py
idpyoidc/client/oauth2/utils.py
idpyoidc/client/oauth2/add_on/__init__.py
idpyoidc/client/oauth2/add_on/dpop.py
idpyoidc/client/oauth2/add_on/identity_assurance.py
idpyoidc/client/oauth2/add_on/jar.py
idpyoidc/client/oauth2/add_on/par.py
idpyoidc/client/oauth2/add_on/pkce.py
idpyoidc/client/oauth2/add_on/status_check.py
idpyoidc/client/oidc/__init__.py
idpyoidc/client/oidc/access_token.py
idpyoidc/client/oidc/authorization.py
idpyoidc/client/oidc/backchannel_authentication.py
idpyoidc-5.0.0.dist-info/LICENSE
idpyoidc-5.0.0.dist-info/METADATA
idpyoidc-5.0.0.dist-info/WHEEL
idpyoidc-5.0.0.dist-info/top_level.txt
idpyoidc-5.0.0.dist-info/RECORD
