Metadata-Version: 2.1
Name: idpyoidc
Version: 5.0.0
Summary: Python implementation of everything OAuth2 and OpenID Connect
Home-page: https://github.com/IdentityPython/idpy-oidc/
Author: Roland Hedberg
Author-email: roland@catalogix.se
License: Apache 2.0
Classifier: Development Status :: 4 - Beta
Classifier: License :: OSI Approved :: Apache Software License
Classifier: Programming Language :: Python :: 3.8
Classifier: Programming Language :: Python :: 3.9
Classifier: Programming Language :: Python :: 3.10
Classifier: Programming Language :: Python :: 3.11
Classifier: Topic :: Software Development :: Libraries :: Python Modules
License-File: LICENSE
Requires-Dist: cryptojwt>=1.8.4
Requires-Dist: pyOpenSSL
Requires-Dist: filelock>=3.0.12
Requires-Dist: pyyaml>=5.1.2
Requires-Dist: jinja2>=2.11.3
Requires-Dist: responses>=0.13.0
